{
    "dataset_name": "Dataset101_Prostate",
    "plans_name": "nnUNetPlans",
    "original_median_spacing_after_transp": [
        3.0000011920928955,
        0.9090999960899353,
        0.9090999960899353
    ],
    "original_median_shape_after_transp": [
        23,
        120,
        220
    ],
    "image_reader_writer": "SimpleITKIO",
    "transpose_forward": [
        0,
        1,
        2
    ],
    "transpose_backward": [
        0,
        1,
        2
    ],
    "configurations": {
        "2d": {
            "data_identifier": "nnUNetPlans_2d",
            "preprocessor_name": "DefaultPreprocessor",
            "batch_size": 114,
            "patch_size": [
                128,
                224
            ],
            "median_image_size_in_voxels": [
                120.0,
                220.0
            ],
            "spacing": [
                0.9090999960899353,
                0.9090999960899353
            ],
            "normalization_schemes": [
                "ZScoreNormalization",
                "ZScoreNormalization",
                "ZScoreNormalization"
            ],
            "use_mask_for_norm": [
                false,
                false,
                false
            ],
            "resampling_fn_data": "resample_data_or_seg_to_shape",
            "resampling_fn_seg": "resample_data_or_seg_to_shape",
            "resampling_fn_data_kwargs": {
                "is_seg": false,
                "order": 3,
                "order_z": 0,
                "force_separate_z": null
            },
            "resampling_fn_seg_kwargs": {
                "is_seg": true,
                "order": 1,
                "order_z": 0,
                "force_separate_z": null
            },
            "resampling_fn_probabilities": "resample_data_or_seg_to_shape",
            "resampling_fn_probabilities_kwargs": {
                "is_seg": false,
                "order": 1,
                "order_z": 0,
                "force_separate_z": null
            },
            "architecture": {
                "network_class_name": "dynamic_network_architectures.architectures.unet.PlainConvUNet",
                "arch_kwargs": {
                    "n_stages": 6,
                    "features_per_stage": [
                        32,
                        64,
                        128,
                        256,
                        512,
                        512
                    ],
                    "conv_op": "torch.nn.modules.conv.Conv2d",
                    "kernel_sizes": [
                        [
                            3,
                            3
                        ],
                        [
                            3,
                            3
                        ],
                        [
                            3,
                            3
                        ],
                        [
                            3,
                            3
                        ],
                        [
                            3,
                            3
                        ],
                        [
                            3,
                            3
                        ]
                    ],
                    "strides": [
                        [
                            1,
                            1
                        ],
                        [
                            2,
                            2
                        ],
                        [
                            2,
                            2
                        ],
                        [
                            2,
                            2
                        ],
                        [
                            2,
                            2
                        ],
                        [
                            2,
                            2
                        ]
                    ],
                    "n_conv_per_stage": [
                        2,
                        2,
                        2,
                        2,
                        2,
                        2
                    ],
                    "n_conv_per_stage_decoder": [
                        2,
                        2,
                        2,
                        2,
                        2
                    ],
                    "conv_bias": true,
                    "norm_op": "torch.nn.modules.instancenorm.InstanceNorm2d",
                    "norm_op_kwargs": {
                        "eps": 1e-05,
                        "affine": true
                    },
                    "dropout_op": null,
                    "dropout_op_kwargs": null,
                    "nonlin": "torch.nn.LeakyReLU",
                    "nonlin_kwargs": {
                        "inplace": true
                    }
                },
                "_kw_requires_import": [
                    "conv_op",
                    "norm_op",
                    "dropout_op",
                    "nonlin"
                ]
            },
            "batch_dice": true
        },
        "3d_fullres": {
            "data_identifier": "nnUNetPlans_3d_fullres",
            "preprocessor_name": "DefaultPreprocessor",
            "batch_size": 6,
            "patch_size": [
                24,
                128,
                224
            ],
            "median_image_size_in_voxels": [
                23.0,
                120.0,
                220.0
            ],
            "spacing": [
                2.999999523162842,
                0.9090999960899353,
                0.9090999960899353
            ],
            "normalization_schemes": [
                "ZScoreNormalization",
                "ZScoreNormalization",
                "ZScoreNormalization"
            ],
            "use_mask_for_norm": [
                false,
                false,
                false
            ],
            "resampling_fn_data": "resample_data_or_seg_to_shape",
            "resampling_fn_seg": "resample_data_or_seg_to_shape",
            "resampling_fn_data_kwargs": {
                "is_seg": false,
                "order": 3,
                "order_z": 0,
                "force_separate_z": null
            },
            "resampling_fn_seg_kwargs": {
                "is_seg": true,
                "order": 1,
                "order_z": 0,
                "force_separate_z": null
            },
            "resampling_fn_probabilities": "resample_data_or_seg_to_shape",
            "resampling_fn_probabilities_kwargs": {
                "is_seg": false,
                "order": 1,
                "order_z": 0,
                "force_separate_z": null
            },
            "architecture": {
                "network_class_name": "dynamic_network_architectures.architectures.unet.PlainConvUNet",
                "arch_kwargs": {
                    "n_stages": 6,
                    "features_per_stage": [
                        32,
                        64,
                        128,
                        256,
                        320,
                        320
                    ],
                    "conv_op": "torch.nn.modules.conv.Conv3d",
                    "kernel_sizes": [
                        [
                            1,
                            3,
                            3
                        ],
                        [
                            3,
                            3,
                            3
                        ],
                        [
                            3,
                            3,
                            3
                        ],
                        [
                            3,
                            3,
                            3
                        ],
                        [
                            3,
                            3,
                            3
                        ],
                        [
                            3,
                            3,
                            3
                        ]
                    ],
                    "strides": [
                        [
                            1,
                            1,
                            1
                        ],
                        [
                            1,
                            2,
                            2
                        ],
                        [
                            2,
                            2,
                            2
                        ],
                        [
                            2,
                            2,
                            2
                        ],
                        [
                            1,
                            2,
                            2
                        ],
                        [
                            1,
                            2,
                            2
                        ]
                    ],
                    "n_conv_per_stage": [
                        2,
                        2,
                        2,
                        2,
                        2,
                        2
                    ],
                    "n_conv_per_stage_decoder": [
                        2,
                        2,
                        2,
                        2,
                        2
                    ],
                    "conv_bias": true,
                    "norm_op": "torch.nn.modules.instancenorm.InstanceNorm3d",
                    "norm_op_kwargs": {
                        "eps": 1e-05,
                        "affine": true
                    },
                    "dropout_op": null,
                    "dropout_op_kwargs": null,
                    "nonlin": "torch.nn.LeakyReLU",
                    "nonlin_kwargs": {
                        "inplace": true
                    }
                },
                "_kw_requires_import": [
                    "conv_op",
                    "norm_op",
                    "dropout_op",
                    "nonlin"
                ]
            },
            "batch_dice": false
        }
    },
    "experiment_planner_used": "ExperimentPlanner",
    "label_manager": "LabelManager",
    "foreground_intensity_properties_per_channel": {
        "0": {
            "max": 3332.0,
            "mean": 316.972412109375,
            "median": 314.0,
            "min": 0.0,
            "percentile_00_5": 72.0,
            "percentile_99_5": 676.0,
            "std": 95.9794692993164
        },
        "1": {
            "max": 32750.0,
            "mean": 893.27734375,
            "median": 873.0,
            "min": 0.0,
            "percentile_00_5": 294.0,
            "percentile_99_5": 1731.0,
            "std": 365.0696716308594
        },
        "2": {
            "max": 30470.0,
            "mean": 249.07376098632812,
            "median": 230.0,
            "min": 0.0,
            "percentile_00_5": 24.0,
            "percentile_99_5": 681.0,
            "std": 333.2242126464844
        }
    }
}